CHANGES.rst
MANIFEST.in
README.rst
setup.cfg
setup.py
docflow/__init__.py
docflow/_version.py
docflow.egg-info/PKG-INFO
docflow.egg-info/SOURCES.txt
docflow.egg-info/dependency_links.txt
docflow.egg-info/requires.txt
docflow.egg-info/top_level.txt
docflow.egg-info/zip-safe
docs/Makefile
docs/conf.py
docs/index.rst
docs/make.bat
docs/_build/doctrees/environment.pickle
docs/_build/doctrees/index.doctree
docs/_build/html/.buildinfo
docs/_build/html/genindex.html
docs/_build/html/index.html
docs/_build/html/objects.inv
docs/_build/html/search.html
docs/_build/html/searchindex.js
docs/_build/html/_sources/index.txt
docs/_build/html/_static/basic.css
docs/_build/html/_static/default.css
docs/_build/html/_static/doctools.js
docs/_build/html/_static/file.png
docs/_build/html/_static/jquery.js
docs/_build/html/_static/minus.png
docs/_build/html/_static/plus.png
docs/_build/html/_static/pygments.css
docs/_build/html/_static/searchtools.js
docs/_build/html/_static/sidebar.js
docs/_build/html/_static/underscore.js
tests/__init__.py
tests/test_docflow.py