Metadata-Version: 1.1
Name: docflow
Version: 0.3.2
Summary: Python Document Workflows
Home-page: http://github.com/jace/pydocflow
Author: Kiran Jonnalagadda
Author-email: jace@pobox.com
License: UNKNOWN
Keywords: workflow
Platform: UNKNOWN
Classifier: Programming Language :: Python
Classifier: Programming Language :: Python :: 2.6
Classifier: Programming Language :: Python :: 2.7
Classifier: License :: OSI Approved :: BSD License
Classifier: Operating System :: OS Independent
Classifier: Intended Audience :: Developers
Classifier: Development Status :: 3 - Alpha
Classifier: Topic :: Software Development :: Libraries
